pachinkoagentic/AIWrapper.py
pachinkoagentic/Capabilities.py
pachinkoagentic/Library.py
pachinkoagentic/Logging.py
pachinkoagentic/MCPWrapper.py
pachinkoagentic/Workflow.py
pachinkoagentic/WorkflowEvent.py
pachinkoagentic/__init__.py
pachinkoagentic-0.0.2.dist-info/licenses/LICENSE
pachinkoagentic-0.0.2.dist-info/METADATA
pachinkoagentic-0.0.2.dist-info/WHEEL
pachinkoagentic-0.0.2.dist-info/top_level.txt
pachinkoagentic-0.0.2.dist-info/RECORD
