Metadata-Version: 2.4
Name: pachinkoagentic
Version: 0.0.2
Summary: agentic toolkit built on MCP that provides description and status of work
Author-email: "Dr. William N. Roney" <dr.william.roney@gmail.com>
Project-URL: Homepage, https://github.com/drwilliamroney/PachinkoAgentic
Keywords: agentic,mcp
Classifier: Operating System :: OS Independent
Classifier: Intended Audience :: Developers
Classifier: Programming Language :: Python :: 3.12
Requires-Python: >=3.12
License-File: LICENSE
Requires-Dist: fastmcp
Requires-Dist: aiohttp
Dynamic: license-file
